spectral_sdk/.DS_Store
spectral_sdk/__init__.py
spectral_sdk/abis/Competition.json
spectral_sdk/abis/CompetitionFactory.json
spectral_sdk/abis/Consumption.json
spectral_sdk/abis/DataTypes.json
spectral_sdk/abis/ERC20Mock.json
spectral_sdk/abis/ICompetition.json
spectral_sdk/abis/ICompetitionFactory.json
spectral_sdk/abis/IConsumption.json
spectral_sdk/abis/IMathHelper.json
spectral_sdk/abis/IModeler.json
spectral_sdk/abis/IServiceAgreement.json
spectral_sdk/abis/MathHelper.json
spectral_sdk/abis/Modeler.json
spectral_sdk/abis/ModelerLibrary.json
spectral_sdk/abis/NewCompetition.json
spectral_sdk/abis/NewModeler.json
spectral_sdk/abis/ProxyBeaconDeployer.json
spectral_sdk/abis/ServiceAgreement.json
spectral_sdk/abis/SpectralToken.json
spectral_sdk/abis/WalletSimple.json
spectral_sdk/abis/__init__.py
spectral_sdk/abis/abis.py
spectral_sdk/abis/process_json_files.sh
spectral_sdk/config_manager.py
spectral_sdk/ezkl_wrapper/__init__.py
spectral_sdk/ezkl_wrapper/ezkl_wrapper.py
spectral_sdk/onnx/input.json
spectral_sdk/onnx/make_inference.py
spectral_sdk/spectral-ai-sdk.code-workspace
spectral_sdk/spectralaisdk.py
spectral_sdk-0.1.14.dist-info/LICENSE
spectral_sdk-0.1.14.dist-info/METADATA
spectral_sdk-0.1.14.dist-info/WHEEL
spectral_sdk-0.1.14.dist-info/entry_points.txt
spectral_sdk-0.1.14.dist-info/RECORD
