Metadata-Version: 2.1
Name: spectral-sdk
Version: 0.1.14
Summary: Spectral SDK allows you to participate in the challenges and competitions on Spectral Finance platform.
Keywords: machine learning,ai,data science,web3
Author: Spectral Finance
Author-email: maciej@spectral.finance
Requires-Python: >=3.11.5,<3.13
Classifier: License :: OSI Approved :: MIT License
Classifier: Programming Language :: Python :: 3
Classifier: Programming Language :: Python :: 3.10
Classifier: Programming Language :: Python :: 3.11
Classifier: Programming Language :: Python :: 3.7
Classifier: Programming Language :: Python :: 3.8
Classifier: Programming Language :: Python :: 3.9
Requires-Dist: click (>=8.1.7,<9.0.0)
Requires-Dist: cloudpickle (>=2.2.1)
Requires-Dist: ezkl (>=1.11.5)
Requires-Dist: numpy (>=1.25.2)
Requires-Dist: onnx (>=1.14.0)
Requires-Dist: onnxruntime (>=1.16.1,<2.0.0)
Requires-Dist: pandas (>=2.1.1,<3.0.0)
Requires-Dist: requests (>=2.31.0)
Requires-Dist: retrying (>=1.3.4,<2.0.0)
Requires-Dist: torch (>=2.0.1)
Requires-Dist: tqdm (>=4.66.1,<5.0.0)
Requires-Dist: web3 (>=6.11.1)
Project-URL: Repository, https://github.com/Spectral-Finance/spectral-ai-sdk
